ff8_mch_charaone/__init__.py
ff8_mch_charaone/main.py
ff8_mch_charaone/export/exporter.py
ff8_mch_charaone/format/bone_indices.py
ff8_mch_charaone/format/formatted_bone.py
ff8_mch_charaone/format/formatted_face.py
ff8_mch_charaone/format/formatted_model.py
ff8_mch_charaone/format/formatted_vertex.py
ff8_mch_charaone/format/uv.py
ff8_mch_charaone/format/animations/bone_pose.py
ff8_mch_charaone/format/animations/formatted_animation.py
ff8_mch_charaone/format/animations/formatted_frame.py
ff8_mch_charaone/format/animations/root_bone_pose.py
ff8_mch_charaone/parse/headers/__parser.py
ff8_mch_charaone/parse/headers/model_header.py
ff8_mch_charaone/parse/mch/mch_header.py
ff8_mch_charaone/parse/model/__parser.py
ff8_mch_charaone/parse/model/bone.py
ff8_mch_charaone/parse/model/face.py
ff8_mch_charaone/parse/model/model_data.py
ff8_mch_charaone/parse/model/skin_object.py
ff8_mch_charaone/parse/model/texture_animation.py
ff8_mch_charaone/parse/model/tim.py
ff8_mch_charaone/parse/model/unknown_data_object.py
ff8_mch_charaone/parse/model/vertex.py
ff8_mch_charaone/parse/model/animations/__parser.py
ff8_mch_charaone/parse/model/animations/animation.py
ff8_mch_charaone/parse/model/animations/frame.py
ff8_mch_charaone/parse/model/animations/pose.py
ff8_mch_charaone/parse/model/animations/theories.md
ff8_mch_charaone/utils/binary_reader.py
ff8_mch_charaone-0.1.0.dist-info/METADATA
ff8_mch_charaone-0.1.0.dist-info/WHEEL
ff8_mch_charaone-0.1.0.dist-info/RECORD
